epoberezkin_how_long/__init__.py
epoberezkin_how_long/how_long.py
epoberezkin_how_long-0.1.2.dist-info/WHEEL
epoberezkin_how_long-0.1.2.dist-info/METADATA
epoberezkin_how_long-0.1.2.dist-info/RECORD
