Metadata-Version: 2.1
Name: epoberezkin-how-long
Version: 0.1.2
Summary: 
License: MIT
Author: Efim Poberezkin
Author-email: efim.poberezkin@gmail.com
Requires-Python: >=3.8,<4.0
Classifier: License :: OSI Approved :: MIT License
Classifier: Programming Language :: Python :: 3
Classifier: Programming Language :: Python :: 3.8
Requires-Dist: pendulum (>=2.1.0,<3.0.0)
